pykeflow/__init__.py
pykeflow/__main__.py
pykeflow-0.1.0.dist-info/licenses/LICENSE
pykeflow-0.1.0.dist-info/METADATA
pykeflow-0.1.0.dist-info/WHEEL
pykeflow-0.1.0.dist-info/entry_points.txt
pykeflow-0.1.0.dist-info/top_level.txt
pykeflow-0.1.0.dist-info/RECORD
